sber_bulb_api-0.0.10.dist-info/licenses/LICENSE
sber_smart_bulb_api/__init__.py
sber_smart_bulb_api/exceptions.py
sber_smart_bulb_api/logger.py
sber_smart_bulb_api/models.py
sber_smart_bulb_api/wrapper.py
sber_bulb_api-0.0.10.dist-info/METADATA
sber_bulb_api-0.0.10.dist-info/WHEEL
sber_bulb_api-0.0.10.dist-info/top_level.txt
sber_bulb_api-0.0.10.dist-info/RECORD
