Metadata-Version: 2.4
Name: sber_bulb_api
Version: 0.0.10
Summary: API wrapper for controlling the Sber smart bulb A60.
Author-email: regenara <jakebv.22@gmail.com>
License: MIT License
Project-URL: repository, https://github.com/regenara/sber_bulb_api
Project-URL: homepage, https://github.com/regenara/sber_bulb_api
License-File: LICENSE
Requires-Dist: pyjwt<3.0.0,>=2.0.0
Requires-Dist: pydantic<3.0.0,>=2.0.0
Requires-Dist: aiohttp<4.0.0,>=3.0.0
Dynamic: license-file
